autromartrizar/__init__.py
autromartrizar/main.py
autromartrizar-2023.9.9.2.dist-info/LICENSE
autromartrizar-2023.9.9.2.dist-info/METADATA
autromartrizar-2023.9.9.2.dist-info/WHEEL
autromartrizar-2023.9.9.2.dist-info/RECORD
